snfa/__init__.py
snfa/aligner.py
snfa/stft.py
snfa/utils.py
snfa/viterbi.py
snfa/models/jp.npz
snfa-0.3.1.dist-info/licenses/LICENCE
snfa-0.3.1.dist-info/METADATA
snfa-0.3.1.dist-info/WHEEL
snfa-0.3.1.dist-info/top_level.txt
snfa-0.3.1.dist-info/RECORD
