Metadata-Version: 2.4
Name: snfa
Version: 0.3.1
Summary: a simple neural forced aligner for phoneme to audio alignment
Author: Patchethium
Project-URL: Homepage, https://github.com/Patchethium/snfa
Classifier: Programming Language :: Python :: 3
Classifier: License :: OSI Approved :: ISC License (ISCL)
Classifier: Operating System :: OS Independent
Requires-Python: >=3.10
License-File: LICENCE
Requires-Dist: numpy
Dynamic: license-file
